{
  "main": {
    "id": "e0cfe49d7f909c71",
    "type": "split",
    "children": [
      {
        "id": "7f1c1d13fd67641d",
        "type": "tabs",
        "children": [
          {
            "id": "2ddaa681e65cc1dc",
            "type": "leaf",
            "state": {
              "type": "markdown",
              "state": {
                "file": "キメレルアップデートPJT/PJT概要.md",
                "mode": "source",
                "source": false
              },
              "icon": "lucide-file",
              "title": "PJT概要"
            }
          }
        ]
      }
    ],
    "direction": "vertical"
  },
  "left": {
    "id": "5870a1f06ec7ae40",
    "type": "split",
    "children": [
      {
        "id": "13192b248e29b63a",
        "type": "tabs",
        "children": [
          {
            "id": "07eb0893dbfe1925",
            "type": "leaf",
            "state": {
              "type": "file-explorer",
              "state": {
                "sortOrder": "alphabetical",
                "autoReveal": true
              },
              "icon": "lucide-folder-closed",
              "title": "ファイルエクスプローラ"
            }
          },
          {
            "id": "06a4ad0da534937e",
            "type": "leaf",
            "state": {
              "type": "search",
              "state": {
                "query": "",
                "matchingCase": false,
                "explainSearch": false,
                "collapseAll": false,
                "extraContext": false,
                "sortOrder": "alphabetical"
              },
              "icon": "lucide-search",
              "title": "検索"
            }
          },
          {
            "id": "7329aa3b5422502d",
            "type": "leaf",
            "state": {
              "type": "bookmarks",
              "state": {},
              "icon": "lucide-bookmark",
              "title": "ブックマーク"
            }
          }
        ],
        "currentTab": 1
      }
    ],
    "direction": "horizontal",
    "width": 300
  },
  "right": {
    "id": "7fa9d59259de9a28",
    "type": "split",
    "children": [
      {
        "id": "c65ddd6b8c365575",
        "type": "tabs",
        "children": [
          {
            "id": "150077b6b53b418a",
            "type": "leaf",
            "state": {
              "type": "backlink",
              "state": {
                "file": "キメレル競合サイト分析.md",
                "collapseAll": false,
                "extraContext": false,
                "sortOrder": "alphabetical",
                "showSearch": false,
                "searchQuery": "",
                "backlinkCollapsed": false,
                "unlinkedCollapsed": true
              },
              "icon": "links-coming-in",
              "title": "キメレル競合サイト分析へのバックリンク"
            }
          },
          {
            "id": "cece6bdb707e6251",
            "type": "leaf",
            "state": {
              "type": "outgoing-link",
              "state": {
                "file": "キメレル競合サイト分析.md",
                "linksCollapsed": false,
                "unlinkedCollapsed": true
              },
              "icon": "links-going-out",
              "title": "キメレル競合サイト分析からのアウトゴーイングリンク"
            }
          },
          {
            "id": "18a41eda9d4983cc",
            "type": "leaf",
            "state": {
              "type": "tag",
              "state": {
                "sortOrder": "frequency",
                "useHierarchy": true,
                "showSearch": false,
                "searchQuery": ""
              },
              "icon": "lucide-tags",
              "title": "タグ"
            }
          },
          {
            "id": "7ac9bf4f0505b8d8",
            "type": "leaf",
            "state": {
              "type": "all-properties",
              "state": {
                "sortOrder": "frequency",
                "showSearch": false,
                "searchQuery": ""
              },
              "icon": "lucide-archive",
              "title": "すべてのプロパティ"
            }
          },
          {
            "id": "746f170a6825ae53",
            "type": "leaf",
            "state": {
              "type": "outline",
              "state": {
                "file": "キメレルアップデートPJT/PJT概要.md",
                "followCursor": false,
                "showSearch": false,
                "searchQuery": ""
              },
              "icon": "lucide-list",
              "title": "PJT概要のアウトライン"
            }
          }
        ]
      }
    ],
    "direction": "horizontal",
    "width": 300,
    "collapsed": true
  },
  "left-ribbon": {
    "hiddenItems": {
      "obsidian-git:Open Git source control": false,
      "switcher:クイックスイッチャーを開く": false,
      "graph:グラフビューを開く": false,
      "canvas:新規キャンバスを作成": false,
      "daily-notes:今日のデイリーノートを開く": false,
      "templates:テンプレートを挿入": false,
      "command-palette:コマンドパレットを開く": false,
      "bases:新規ベースを作成": false,
      "obsidian-kanban:Create new board": false
    }
  },
  "active": "2ddaa681e65cc1dc",
  "lastOpenFiles": [
    "キメレルアップデートPJT/99_日々の蓄積/野中さんMTG メモ.md",
    "キメレルアップデートPJT/PJT概要.md",
    "キメレルアップデートPJT/99_日々の蓄積/気づき・所感.md",
    "キメレルアップデートPJT/99_日々の蓄積/改善案整理.md",
    "キメレルアップデートPJT/01_ 課題からアップデートする考え方/日々の進め方/04-22.md",
    "キメレルアップデートPJT/01_ 課題からアップデートする考え方/日々の進め方/04-20.md",
    "キメレルアップデートPJT/02_理想状態と今をつなぐ考え方/理想状態の言語化 ver3.md",
    "キメレルアップデートPJT/タスク管理.md",
    "キメレルアップデートPJT/02_理想状態と今をつなぐ考え方/理想状態の言語化 ver2.md",
    "谷口さん/Open Time.md",
    "キメレルアップデートPJT/このフォルダの開発方針.md",
    "キメレルアップデートPJT/02_理想状態と今をつなぐ考え方/理想状態の言語化 ver1.md",
    "キメレルアップデートPJT/99_日々の蓄積/反省点.md",
    "キメレルアップデートPJT/03_キメレルのVPを考えるやり方/VP.md",
    "キメレルアップデートPJT/04_改善策を考える？",
    "キメレルアップデートPJT/01_ 課題からアップデートする考え方/キメレルの課題.md",
    "キメレルアップデートPJT/01_ 課題からアップデートする考え方/日々の進め方/04-15.md",
    "キメレルアップデートPJT/03_キメレルのVPを考えるやり方",
    "キメレルアップデートPJT/01_キメレル競合分析/PJT概要.md",
    "キメレルアップデートPJT/01_キメレル競合分析/調査内容整理.md",
    "キメレルアップデートPJT/02_理想状態と今をつなぐ考え方",
    "キメレルアップデートPJT",
    "無題のフォルダ/無題のファイル.md",
    "無題のファイル 1.base",
    "無題のファイル.base",
    "無題のファイル.canvas",
    "谷口さん/OpenTime/Open Time.md",
    "その他/コリンの約束ワーク.md",
    "ノート名.md",
    "ようこそ.md",
    "無題のファイル 2.base",
    "キメレルアップデートPJT/99_日々の蓄積",
    "キメレルアップデートPJT/01_ 課題からアップデートする考え方/日々の進め方",
    "キメレルアップデートPJT/01_ 課題からアップデートする考え方"
  ]
}